pyBinaryClust/DE.py
pyBinaryClust/DR.py
pyBinaryClust/IO.py
pyBinaryClust/__init__.py
pyBinaryClust/clustering.py
pyBinaryClust/convenience.py
pyBinaryClust/plot.py
pyBinaryClust-0.0.10.dist-info/METADATA
pyBinaryClust-0.0.10.dist-info/WHEEL
pyBinaryClust-0.0.10.dist-info/top_level.txt
pyBinaryClust-0.0.10.dist-info/RECORD
